my_Package/__init__.py
my_Package/module1.py
my_package_Goga-0.1.0.dist-info/LICENCE
my_package_Goga-0.1.0.dist-info/METADATA
my_package_Goga-0.1.0.dist-info/WHEEL
my_package_Goga-0.1.0.dist-info/top_level.txt
my_package_Goga-0.1.0.dist-info/RECORD
