Metadata-Version: 2.1
Name: my_package_Goga
Version: 0.1.0
Summary: Module_Personal
Home-page: https://github.com/yourusername/my-package
Author: Jaskaran Singh Goga
Author-email: gogaismyname@example.com
Classifier: Programming Language :: Python :: 3
Classifier: License :: OSI Approved :: MIT License
Classifier: Operating System :: OS Independent
Requires-Python: >=3.6
License-File: LICENCE
